setup.py
request_get.egg-info/PKG-INFO
request_get.egg-info/SOURCES.txt
request_get.egg-info/dependency_links.txt
request_get.egg-info/requires.txt
request_get.egg-info/top_level.txt
requests/__init__.py
requests/__version__.py
requests/_internal_utils.py
requests/adapters.py
requests/api.py
requests/auth.py
requests/certs.py
requests/compat.py
requests/cookies.py
requests/exceptions.py
requests/help.py
requests/hooks.py
requests/models.py
requests/packages.py
requests/sessions.py
requests/status_codes.py
requests/structures.py
requests/utils.py