Metadata-Version: 2.1
Name: request-get
Version: 0.0.1
Summary: request-get
Author: request-get
